{
    "dungeonConfig": [
        {
            "entity": {
                "name": "Cave"
            },
            "defaultDungeonLocationName": "Cave Entrance",
            "dungeonLocationConfig": [
                {
                    "entity": {
                        "name": "Cave Entrance",
                        "description": "A large cave entrance."
                    },
                    "north_location_name": "Cave Tunnel"
                },
                {
                    "entity": {
                        "name": "Cave Tunnel",
                        "description": "A cave tunnel descends into the mountain."
                    },
                    "north_location_name": "Cave Room",
                    "west_location_name": "Dark Cave Tunnel",
                    "south_location_name": "Cave Entrance"
                },
                {
                    "entity": {
                        "name": "Dark Cave Tunnel",
                        "description": "A dark cave tunnel descends deeper into the mountain."
                    },
                    "east_location_name": "Cave Tunnel",
                    "west_location_name": "Dark Cave Room"
                },
                {
                    "entity": {
                        "name": "Cave Room",
                        "description": "A large cave room."
                    },
                    "south_location_name": "Cave Tunnel"
                },
                {
                    "entity": {
                        "name": "Dark Cave Room",
                        "description": "A large dark cave room."
                    },
                    "east_location_name": "Dark Cave Tunnel"
                }
            ],
            "dungeonMonsterConfig": [
                {
                    "entity": {
                        "name": "Goblin"
                    },
                    "location_name": "Cave Tunnel"
                }
            ],
            "dungeonObjectConfig": [
                {
                    "entity": {
                        "name": "Silver Chain"
                    },
                    "location_name": "Cave Room"
                }
            ]
        }
    ]
}
